<?xml version="1.0"?>
<opencv_storage>
<my_svm type_id="opencv-ml-svm">
  <svm_type>C_SVC</svm_type>
  <kernel><type>LINEAR</type></kernel>
  <C>2.5000000000000000e+00</C>
  <term_criteria><epsilon>2.2204460492503131e-16</epsilon>
    <iterations>100000</iterations></term_criteria>
  <var_all>2688</var_all>
  <var_count>2688</var_count>
  <class_count>2</class_count>
  <class_labels type_id="opencv-matrix">
    <rows>1</rows>
    <cols>2</cols>
    <dt>i</dt>
    <data>
      -1 1</data></class_labels>
  <sv_total>1</sv_total>
  <support_vectors>
    <_>
      -6.68236136e-01 -1.82867855e-01 -1.67052060e-01 5.81026435e-01
      -1.40532553e+00 4.24237669e-01 -6.77057207e-01 6.61473721e-02
      5.78948975e-01 -5.93987703e-01 1.19483554e+00 7.50326335e-01
      -2.85125941e-01 3.23563695e-01 -2.25998655e-01 -3.82931054e-01
      -1.06995046e-01 -8.75303924e-01 -4.41337019e-01 -6.37673557e-01
      7.00611621e-02 7.64072597e-01 -1.15960240e+00 -2.41851583e-01
      -2.38050029e-01 -4.48501647e-01 -1.12828769e-01 -1.24343646e+00
      -9.74376947e-02 3.79523307e-01 1.82695135e-01 0. -8.24169993e-01
      3.81856918e-01 3.77787143e-01 8.21735561e-01 5.61986387e-01
      -1.70115158e-01 6.73830092e-01 -1.22632885e+00 -4.18241262e-01
      -9.31393132e-02 3.61398906e-01 -4.86404955e-01 -1.18115497e+00
      -8.81142318e-01 -2.66903155e-02 -4.86375153e-01 4.02552187e-01
      3.10101509e-01 7.50627220e-01 -3.51065814e-01 7.87923455e-01
      -3.36535215e-01 7.87787735e-01 4.68396157e-01 2.38514513e-01
      -1.91594750e-01 2.74664968e-01 -6.41418815e-01 1.77613914e-01
      -5.95715165e-01 1.62675217e-01 0. -6.72213376e-01 -3.91572893e-01
      -1.24407423e+00 1.10393035e+00 2.72490740e-01 -2.02106670e-01
      1.49458528e-01 2.07476258e-01 -3.50116104e-01 3.80962163e-01
      5.98086417e-02 4.32233423e-01 -3.66044730e-01 -3.54053050e-01
      -6.45621419e-01 1.11130118e+00 3.01051795e-01 1.13874733e+00
      5.21710455e-01 3.58624429e-01 -4.87547256e-02 -5.58851600e-01
      5.79237819e-01 2.42151573e-01 -6.86889067e-02 8.97069275e-02
      -9.87776279e-01 2.55854428e-01 -6.98281467e-01 3.11588883e-01
      5.70021570e-01 0. 2.27677181e-01 -2.70595282e-01 1.30877182e-01
      1.65767759e-01 -1.77458048e-01 4.43979591e-01 8.70744944e-01
      -1.20706451e+00 -1.60939887e-01 -7.86592543e-01 9.97931957e-01
      3.54757011e-01 1.14634025e+00 -4.70307440e-01 -5.21691084e-01
      -1.20039068e-01 5.05739152e-01 -2.67408639e-01 6.70518696e-01
      -8.06420147e-01 6.51884973e-02 1.27231687e-01 2.84435213e-01
      7.58809865e-01 -5.86328566e-01 1.52415082e-01 4.15546954e-01
      1.08408369e-01 6.22622788e-01 2.56374240e-01 -5.81191123e-01 0.
      8.05594102e-02 -7.12440848e-01 -1.16951263e+00 8.87628913e-01
      -4.32890683e-01 1.15717426e-01 1.04951286e+00 2.48043850e-01
      8.10923874e-02 -7.40873039e-01 3.65713894e-01 5.89406371e-01
      -4.66386467e-01 6.17766827e-02 -6.69552863e-01 -1.40212488e+00
      -5.77798665e-01 5.18137217e-01 7.17911541e-01 1.34742752e-01
      -3.20849508e-01 3.93241465e-01 2.01045692e-01 1.15570378e+00
      -5.29312074e-01 8.08461607e-01 -3.10738832e-01 -5.97305775e-01
      7.86421672e-02 -7.37969339e-01 2.31813446e-01 0. -7.23506689e-01
      5.77452481e-01 -8.73037893e-03 -5.15508115e-01 5.61170757e-01
      -1.19966376e+00 3.63629222e-01 2.67210640e-02 -2.50779659e-01
      -5.61690450e-01 -1.07644606e+00 7.61869401e-02 -4.74565566e-01
      7.91267455e-02 -1.45293862e-01 -7.05958903e-02 7.34990418e-01
      1.06375086e+00 -2.53396749e-01 2.74071932e-01 -4.72428322e-01
      -2.91424870e-01 -1.07691586e+00 -2.28358030e-01 8.37606251e-01
      -6.56083450e-02 -5.17135561e-01 3.33002567e-01 3.77085835e-01
      -1.05637848e+00 -3.81434917e-01 0. -2.67160475e-01 8.78410876e-01
      8.08762848e-01 -8.12702000e-01 -4.93373543e-01 8.76749903e-02
      7.42540598e-01 2.43313998e-01 -1.15068185e+00 3.91182452e-02
      -4.08513695e-01 1.70392871e+00 -4.50232863e-01 1.01632428e+00
      -1.05827689e-01 -6.20762169e-01 4.36029583e-01 -4.17213470e-01
      6.89634800e-01 -6.44159019e-01 8.00288677e-01 4.47402000e-01
      -5.77397823e-01 -4.35691535e-01 5.18365979e-01 2.67716467e-01
      4.14176315e-01 3.37776616e-02 -3.36798370e-01 5.86111724e-01
      2.96559423e-01 0. -1.88336205e+00 3.65876019e-01 -3.76715422e-01
      -1.38755620e+00 5.23895502e-01 4.74558055e-01 1.79754719e-01
      -3.52043390e-01 5.50863028e-01 4.51391250e-01 5.73718786e-01
      -4.65876311e-01 5.26610672e-01 -7.32349455e-01 7.37232685e-01
      2.34597772e-01 -3.62696737e-01 9.33287561e-01 7.13882521e-02
      -9.34754848e-01 -1.86605051e-01 -6.41646206e-01 -2.18487289e-02
      -7.64302909e-01 2.45662704e-01 -6.62834167e-01 8.09745550e-01
      -2.78628301e-02 7.16890812e-01 6.71545640e-02 -7.60338187e-01 0.
      -4.50206757e-01 5.55483028e-02 -5.47196679e-02 6.59253180e-01
      9.28404570e-01 -6.13652945e-01 5.60840130e-01 1.16763487e-01
      -9.31821704e-01 3.46339911e-01 2.96469688e-01 2.26366699e-01
      -4.44000393e-01 -8.22868347e-01 -8.68537799e-02 -4.83079225e-01
      -2.43943170e-01 -6.21299166e-03 -8.58058810e-01 -5.83615541e-01
      3.69995147e-01 6.84025362e-02 6.92979813e-01 -3.59736562e-01
      -2.19178230e-01 2.27547616e-01 2.37146482e-01 -4.37558621e-01
      -5.14568165e-02 -4.90454912e-01 5.32878995e-01 0. 3.59938204e-01
      -7.61507750e-01 9.33247656e-02 4.56987500e-01 -6.97188377e-01
      8.06063652e-01 6.26406252e-01 -3.36906582e-01 3.16564351e-01
      -2.04953134e-01 -1.96560070e-01 -4.06090647e-01 -3.02987188e-01
      -2.15535596e-01 -7.62066126e-01 -4.86316383e-01 2.32291609e-01
      9.77448300e-02 -5.36960602e-01 6.04062751e-02 3.58387589e-01
      -3.75165880e-01 -4.04853165e-01 1.12719297e+00 1.47793248e-01
      7.81817213e-02 -5.34211457e-01 -5.75417995e-01 5.79832494e-01
      -5.36917150e-01 -1.18401170e-01 0. 1.82102725e-01 6.88141763e-01
      -5.42903960e-01 5.85965905e-03 6.53824568e-01 2.70380378e-01
      -1.83671117e+00 -2.28461727e-01 1.39481381e-01 -1.71921825e+00
      1.34710765e+00 -1.76275805e-01 2.77964324e-01 6.64042711e-01
      -8.45418036e-01 8.29451799e-01 -7.45947063e-01 9.89765406e-01
      -6.61789402e-02 8.73283386e-01 -4.98207599e-01 2.21209213e-01
      -5.73119223e-01 -1.93715431e-02 -6.88971102e-01 1.02992788e-01
      -8.59321713e-01 -1.72905400e-01 -5.05221546e-01 -8.75042826e-02
      7.43564129e-01 0. 1.40919343e-01 -1.14938843e+00 4.37378764e-01
      7.61814952e-01 1.27402261e-01 -6.19013965e-01 -9.40050542e-01
      8.11898470e-01 7.24134743e-01 -8.89539421e-02 -2.98287988e-01
      2.99123138e-01 -5.70816994e-01 -1.63138241e-01 6.37247860e-01
      -2.98334658e-01 1.51186883e+00 -6.11366093e-01 7.59726644e-01
      5.10742843e-01 1.58615515e-01 3.87353987e-01 -7.30568588e-01
      1.94247067e-01 5.88776588e-01 8.05605650e-01 -1.03708005e+00
      6.30158842e-01 3.81555259e-01 -1.83899730e-01 -4.91971254e-01 0.
      -8.94692302e-01 1.05811223e-01 1.11445272e+00 9.60392416e-01
      5.13066888e-01 1.95240462e+00 2.79522866e-01 3.91374171e-01
      -9.07917619e-01 -4.72313553e-01 -7.21815750e-02 -9.18838203e-01
      4.23608840e-01 5.90425074e-01 -1.34906864e+00 -1.09008878e-01
      -4.15774405e-01 1.04433620e+00 5.55204302e-02 -9.30401683e-01
      2.00295463e-01 1.11229217e+00 -7.77639508e-01 -8.14846337e-01
      -4.96242404e-01 -7.75421381e-01 9.14999366e-01 -6.14164531e-01
      7.07780957e-01 -1.26269102e-01 1.08651376e+00 0. 2.56612211e-01
      1.12443268e-01 -1.21801245e+00 1.90463051e-01 -2.43224762e-02
      -4.16853987e-02 6.44621551e-01 -9.63190421e-02 2.23913237e-01
      -4.76321839e-02 7.67523870e-02 -4.82522726e-01 5.31197727e-01
      1.36500016e-01 8.89151216e-01 -7.13611782e-01 -8.07960272e-01
      -1.36125669e-01 2.94845313e-01 8.44768405e-01 1.86039358e-01
      -5.24052680e-01 -1.02184333e-01 -1.46509454e-01 -8.36600482e-01
      6.26299560e-01 1.21958099e-01 -1.07653487e+00 6.65230036e-01
      -1.26572526e+00 1.43824923e+00 0. 8.11505988e-02 1.00952256e+00
      -2.19880670e-01 -9.54628289e-01 -2.50177234e-01 1.44975603e-01
      8.82118106e-01 2.60273188e-01 -1.28601700e-01 -3.11727852e-01
      9.57040712e-02 -7.29399860e-01 1.69070512e-01 4.83084738e-01
      -6.61544263e-01 -1.04717851e-01 -4.44023281e-01 -6.08003020e-01
      -7.97296941e-01 8.54941845e-01 -5.93878210e-01 -3.87952715e-01
      -3.48743677e-01 4.22201335e-01 5.39776623e-01 -7.02504933e-01
      -5.98463893e-01 -5.63812017e-01 2.32787728e-01 -5.80483615e-01
      3.04909319e-01 0. -1.32534176e-01 1.15485482e-01 1.07542895e-01
      1.20012665e+00 -4.12688792e-01 1.36683479e-01 -9.18163002e-01
      -3.17935199e-01 9.25587535e-01 1.82077631e-01 -6.08522534e-01
      -5.10654390e-01 2.33368099e-01 -8.44479144e-01 2.95516551e-01
      9.46667865e-02 -7.52816796e-01 4.10802215e-01 -7.95733094e-01
      -7.69652307e-01 -7.36540735e-01 9.03811932e-01 5.74055612e-01
      -2.41357222e-01 1.50457874e-03 -5.30408323e-01 6.97810233e-01
      -3.45892102e-01 1.86418518e-01 -5.45890152e-01 3.30159634e-01 0.
      -3.07448000e-01 -1.78666320e-03 -1.48590803e-01 6.14121377e-01
      2.02748090e-01 -3.45477730e-01 4.62478966e-01 -1.24231863e+00
      1.83321446e-01 2.12788150e-01 -1.61730215e-01 -7.63744652e-01
      -5.97379923e-01 7.27572620e-01 2.35303536e-01 4.71192479e-01
      -5.56062281e-01 1.60303563e-01 4.69483823e-01 -9.09770131e-02
      7.45143294e-01 -7.94941604e-01 -5.89404225e-01 3.23799819e-01
      -8.49101007e-01 3.61497521e-01 8.10068965e-01 -1.19695902e+00
      1.11563337e+00 -8.12007129e-01 4.90423709e-01 0. -3.61626208e-01
      -7.61353254e-01 9.48812366e-02 4.16651875e-01 2.20563817e+00
      4.54638377e-02 8.44784379e-01 1.19382548e+00 3.03367049e-01
      -8.88804615e-01 9.37629759e-01 -1.91325679e-01 -7.02814851e-03
      -9.23539996e-01 1.04889892e-01 2.32550383e-01 -8.76386881e-01
      2.27839500e-01 -1.22851662e-01 8.74450088e-01 -6.52934849e-01
      -4.95167822e-01 -1.47821677e+00 1.57685131e-01 9.86430705e-01
      1.72362432e-01 -9.77945924e-01 4.25056845e-01 7.70187199e-01
      -4.60705698e-01 4.89902794e-01 0. 4.41402704e-01 -1.78447917e-01
      2.66471088e-01 -1.65331423e-01 -1.16480100e+00 3.22551399e-01
      -3.34496439e-01 -7.78745472e-01 4.96125251e-01 2.74384797e-01
      3.01014692e-01 -3.54346752e-01 -5.62677562e-01 5.64996060e-03
      7.80701041e-01 5.64470947e-01 -8.03456485e-01 -1.33903623e-01
      -2.13302112e+00 7.47157574e-01 -8.17069635e-02 -5.83615862e-02
      5.00457466e-01 -1.68856859e-01 1.94781601e-01 8.05007398e-01
      -4.35484320e-01 6.45479783e-02 -1.54918924e-01 -2.23834619e-01
      -1.68241590e-01 0. 1.04535663e+00 3.51765230e-02 -1.06430268e+00
      4.52848434e-01 -2.87815839e-01 3.01453590e-01 -7.54519105e-02
      -1.86562523e-01 9.83824015e-01 -1.55202270e-01 -1.58462870e+00
      6.12942338e-01 5.85439727e-02 -8.38162839e-01 6.28340900e-01
      -3.01365972e-01 6.67828739e-01 1.49156108e-01 1.82156898e-02
      -7.58422390e-02 6.24612868e-01 9.39117312e-01 6.58057272e-01
      5.84982455e-01 -5.89068234e-01 -3.95958334e-01 1.13755000e+00
      5.53050339e-01 4.29981142e-01 -6.76584780e-01 -9.80991572e-02 0.
      1.77647825e-02 -4.98264760e-01 9.19855654e-01 4.48767304e-01
      -3.27422827e-01 -7.24135399e-01 4.88161415e-01 6.75940871e-01
      -4.88263607e-01 -4.05925900e-01 5.95742285e-01 -6.62674427e-01
      -2.49676451e-01 -4.74673808e-01 -4.37628955e-01 -1.48021325e-01
      -2.88061380e-01 -7.05755234e-01 -9.78357811e-03 9.63090837e-01
      1.03238118e+00 5.82866073e-01 8.37458730e-01 4.88952547e-01
      -4.49201256e-01 1.45142484e+00 -9.17949080e-02 6.83414400e-01
      -5.75739026e-01 -7.40750670e-01 -4.34302241e-01 0. -4.29255426e-01
      -4.07865822e-01 8.06045651e-01 5.71353018e-01 -9.05530274e-01
      -7.45148733e-02 2.05688268e-01 6.00494623e-01 -3.67388159e-01
      -9.42603052e-02 -5.16811192e-01 -8.32002163e-02 -1.50495190e-02
      -5.75890303e-01 -7.08236992e-01 -1.84340373e-01 -6.15575254e-01
      6.56548023e-01 -1.28565341e-01 1.28042921e-01 1.17078006e+00
      -6.97826743e-01 4.90154654e-01 4.65935737e-01 9.77962196e-01
      1.11890805e+00 8.99231076e-01 -7.21130073e-01 -2.88645536e-01
      4.61339325e-01 -4.59317267e-01 0. 1.49606183e-01 7.70923555e-01
      -3.11045527e-01 9.63981673e-02 1.38819680e-01 -2.50780970e-01
      4.48718578e-01 -1.12733066e+00 -2.13563532e-01 9.32394207e-01
      1.46293208e-01 6.97381377e-01 -2.76246756e-01 5.84030032e-01
      -8.84773195e-01 7.88265914e-02 5.04470646e-01 -1.82680655e+00
      5.64323775e-02 1.31252718e+00 -5.27582109e-01 -1.26021802e-01
      -1.02043087e-02 7.34507024e-01 1.33871496e+00 4.11080241e-01
      -1.00410897e-02 -7.38150418e-01 -4.01279092e-01 5.92776954e-01
      3.85111064e-01 0. 2.70278871e-01 4.68221992e-01 -7.42325485e-01
      -4.72839862e-01 6.50098085e-01 -1.06999779e+00 -8.71073604e-02
      2.29845896e-01 -7.38065317e-02 5.44998348e-01 -5.82214026e-03
      -1.14041018e+00 6.80485666e-01 1.23576605e+00 -2.62401998e-01
      -4.92815107e-01 -5.36360562e-01 4.66581285e-01 -2.21898031e+00
      -4.33592856e-01 3.75370294e-01 3.99015814e-01 -1.11640537e+00
      7.68149436e-01 2.30316535e-01 -1.97964441e-02 5.80489933e-01
      -4.67928767e-01 3.90760005e-01 1.19993687e-01 -2.01974943e-01 0.
      3.06812860e-02 -4.84015465e-01 3.90090674e-01 3.12041454e-02
      5.45026839e-01 -2.77892470e-01 3.83890122e-01 5.29951811e-01
      4.78507280e-02 4.30477917e-01 -3.41330618e-01 -6.42635942e-01
      3.47676992e-01 2.74911046e-01 1.19900942e-01 -1.39420223e+00
      6.41047537e-01 -7.47656748e-02 5.41499615e-01 5.60735106e-01
      1.09602356e+00 7.58357704e-01 -6.76498890e-01 -3.89661998e-01
      -6.01544857e-01 -3.02889682e-02 1.23348904e+00 4.40248132e-01
      -4.62302595e-01 9.27383184e-01 -6.42349660e-01 0. -6.11341834e-01
      -4.28394042e-02 -3.26569825e-01 4.04381454e-01 2.18135208e-01
      -6.44138694e-01 8.97239372e-02 1.03337133e+00 -1.09417856e+00
      -6.48576915e-01 -4.85175133e-01 -2.09940150e-01 -5.75134993e-01
      1.76808119e-01 2.30892450e-02 3.10403019e-01 -4.98104483e-01
      -2.83982717e-02 -1.27487552e+00 3.49548399e-01 2.37557486e-01
      -4.32805866e-01 -1.19963694e+00 1.39656708e-01 9.29910719e-01
      5.98092973e-01 1.23540834e-01 -1.09914351e+00 1.85150221e-01
      1.65812355e-02 -4.73648429e-01 0. 3.81132394e-01 2.44228750e-01
      2.21646979e-01 -2.24507570e-01 6.81924820e-01 3.19022745e-01
      -1.01358473e+00 9.17165220e-01 9.85512324e-03 -4.63004082e-01
      5.31822920e-01 5.00250041e-01 7.84987986e-01 6.50360405e-01
      -6.89252496e-01 -1.10762075e-01 -1.24882810e-01 -5.92920959e-01
      7.11009920e-01 7.96987042e-02 -1.16395986e+00 -3.60858172e-01
      4.27292466e-01 -1.22148372e-01 -3.94501716e-01 -7.75700808e-02
      6.30595207e-01 -3.63638133e-01 8.72634351e-01 3.38658720e-01
      1.06214687e-01 0. -6.15850128e-02 -2.20771849e-01 8.42375338e-01
      -9.69777703e-01 3.84387553e-01 8.54994655e-01 -1.23667650e-01
      2.05204234e-01 4.53301072e-01 2.17129812e-01 -7.34303653e-01
      -3.24315935e-01 -1.30597353e-02 -8.59935045e-01 9.28818107e-01
      4.44112480e-01 4.08497900e-01 2.67866522e-01 5.80881178e-01
      5.00918329e-01 -1.86262563e-01 -2.09292576e-01 2.87534952e-01
      5.77446938e-01 -5.70505619e-01 -1.37932289e+00 -1.46382287e-01
      8.85454342e-02 3.28919828e-01 -4.11053032e-01 7.94623971e-01 0.
      -7.24546611e-01 -1.08129108e+00 1.03112435e+00 1.89194515e-01
      -7.27665275e-02 -1.53121486e-01 6.20069921e-01 -4.52226549e-01
      2.84254998e-01 -9.43659782e-01 1.92786992e-01 -3.56538624e-01
      2.17146352e-01 -4.25352931e-01 5.33117056e-01 -7.10606933e-01
      -2.36090735e-01 -2.02487797e-01 -1.42015910e+00 1.86820924e-01
      7.99106658e-01 7.29131579e-01 1.82274967e-01 -1.16901302e+00
      -5.37990272e-01 2.76713341e-01 4.93062735e-01 1.35377888e-02
      -3.47387969e-01 -9.59850192e-01 2.13725001e-01 0. 4.47568208e-01
      -2.00563833e-01 5.98988712e-01 5.42513609e-01 -1.39749944e-01
      1.92006499e-01 -9.27671418e-02 1.42975643e-01 -3.18853438e-01
      -4.47073057e-02 1.20246455e-01 5.06307065e-01 -1.49320519e+00
      2.20605999e-01 -5.20268194e-02 5.22070944e-01 -7.26878464e-01
      -3.21188480e-01 7.09987938e-01 1.33295643e+00 -2.21326035e-02
      -5.56694031e-01 -7.69924581e-01 4.89387736e-02 7.60722101e-01
      1.04703307e+00 4.80631620e-01 1.05548871e+00 -5.56769490e-01
      1.11886956e-01 -6.56169951e-01 0. 2.59568065e-01 -1.34686992e-01
      4.89993095e-01 -1.21218002e+00 7.19487488e-01 -1.02232921e+00
      5.26583016e-01 5.13959900e-02 -2.14500284e+00 4.89042372e-01
      -4.90637720e-01 1.36149895e+00 2.35545486e-01 9.13113534e-01
      4.58644331e-01 4.39355910e-01 2.40426272e-01 5.90968370e-01
      -7.69812524e-01 -9.20593262e-01 -2.70076066e-01 -9.88764048e-01
      -9.66637552e-01 -3.31458822e-02 9.90595102e-01 1.86066419e-01
      -4.78635132e-02 6.64822534e-02 2.21318260e-01 6.01652145e-01
      -5.47045842e-02 0. -6.13795817e-01 1.37704507e-01 -8.25093806e-01
      -5.54033458e-01 1.55133522e+00 4.03189421e-01 1.27349210e+00
      -6.88326359e-01 1.70584202e+00 -2.00306222e-01 -1.00808688e-01
      2.23800942e-01 1.91423044e-01 -1.31485915e+00 6.52249634e-01
      -1.18905234e+00 -6.04821026e-01 1.18060338e+00 -8.39284241e-01
      1.61132550e+00 -8.63854527e-01 -5.06119849e-03 2.86650175e-04
      2.84492642e-01 4.92778122e-02 -6.77230179e-01 8.22335780e-01
      3.47136378e-01 -2.63466954e-01 3.00919265e-01 1.94546342e-01 0.
      -6.46223426e-01 7.67124474e-01 3.35312247e-01 1.24792494e-02
      7.63202667e-01 5.52929044e-02 -1.32370472e-01 -1.10516763e+00
      1.23129681e-01 -1.08326304e+00 -1.48547304e+00 -2.75665939e-01
      -5.85979700e-01 1.07264347e-01 2.77661532e-01 3.08757335e-01
      -5.69916852e-02 -7.47011781e-01 3.36292893e-01 1.17194676e+00
      2.48019651e-01 -1.07629098e-01 -1.92223152e-03 -8.18036497e-01
      5.83662093e-01 2.53253818e-01 2.94096619e-01 6.00001141e-02
      -6.98804677e-01 -9.33826342e-02 -8.55451703e-01 0. -9.55291271e-01
      1.89628899e-01 -1.33259320e+00 1.26578376e-01 1.95779845e-01
      7.23634839e-01 -1.23204505e-02 5.86384237e-01 6.67845488e-01
      -6.63504601e-01 -8.70198846e-01 1.38236165e-01 4.72090036e-01
      9.54611376e-02 2.97743142e-01 -5.99043489e-01 -2.91514069e-01
      -1.46966434e+00 6.56736195e-01 -1.76709052e-03 3.77988964e-01
      7.01149404e-01 -1.12696528e+00 3.41788560e-01 9.31392387e-02
      4.12007093e-01 1.32128859e+00 3.52027193e-02 -8.51695478e-01
      3.10412675e-01 -7.67053664e-01 0. -3.39256048e-01 1.95914137e+00
      -4.99361694e-01 1.09218800e+00 3.43578309e-01 1.49054432e+00
      -2.38670528e-01 -7.32904494e-01 1.12183280e-01 -6.13533914e-01
      1.01639044e+00 -6.59342587e-01 -1.41730940e+00 3.86146396e-01
      -1.04309356e+00 1.13546051e-01 7.61879385e-02 -2.20119543e-02
      -6.37324095e-01 6.96904123e-01 -6.93752348e-01 -1.56605124e-01
      2.20682785e-01 1.36786669e-01 -1.49466127e-01 -8.62160027e-01
      1.51807463e+00 1.48628831e-01 1.26280889e-01 4.75706965e-01
      -2.67703891e-01 0. 3.52008820e-01 -1.51138163e+00 -1.41281158e-01
      4.82068568e-01 -5.59990287e-01 1.87389269e-01 -1.11548054e+00
      5.97152054e-01 -2.33411595e-01 2.38906682e-01 6.27966166e-01
      2.50714928e-01 5.24636507e-01 7.11456537e-01 4.64122921e-01
      2.09085599e-01 1.48794222e+00 -6.51038706e-01 -8.89144838e-01
      -2.63230741e-01 -1.17272198e-01 6.94075048e-01 -1.63373724e-01
      -4.31056499e-01 -9.95785534e-01 -1.12912945e-01 -3.04842442e-01
      5.68889499e-01 1.73417985e-01 5.36576994e-02 1.09530814e-01 0.
      1.30681288e+00 -3.26016217e-01 -1.24451499e-02 9.24798191e-01
      7.90600255e-02 9.78410900e-01 2.59161711e-01 -1.61279058e+00
      7.91309476e-01 7.00908244e-01 3.89331996e-01 -1.96147710e-01
      -2.27524728e-01 -2.39331603e-01 2.77849257e-01 -7.75368810e-01
      8.09931606e-02 -1.58136594e+00 2.44632885e-01 1.47038186e+00
      1.77088141e-01 1.65235627e+00 -1.03367698e+00 -3.23524982e-01
      -2.03408554e-01 3.54398876e-01 2.89472073e-01 3.97519469e-01
      -7.82551542e-02 -6.35702908e-01 7.01876462e-01 0. -1.86637063e-02
      3.81216645e-01 -2.62802362e-01 -1.77928722e+00 -4.28145140e-01
      1.00545481e-01 -2.63164192e-01 5.88970967e-02 -4.28054214e-01
      -1.21242061e-01 3.48394513e-01 2.27822840e-01 -3.58448178e-02
      3.22164148e-01 9.17808831e-01 9.63695869e-02 1.26460627e-01
      -7.38627553e-01 -9.00110960e-01 -4.26419109e-01 -2.46526688e-01
      -6.13273680e-01 4.31798875e-01 3.89485717e-01 2.85086147e-02
      4.73197877e-01 -1.21579456e+00 1.40275553e-01 -1.52952686e-01
      3.95735860e-01 -1.08834445e+00 0. -8.20413768e-01 4.81231868e-01
      -6.91456124e-02 7.59369612e-01 -6.40893698e-01 5.53679407e-01
      -1.58421844e-01 -9.85001564e-01 -2.36733034e-01 9.57052112e-01
      7.99085498e-02 -5.46310842e-01 -7.88380265e-01 -6.92425728e-01
      1.13162562e-01 2.19816696e-02 6.81942761e-01 3.07239264e-01
      1.38691679e-01 -3.12581718e-01 -6.68213725e-01 1.68859696e+00
      1.76884100e-01 5.95596492e-01 -2.27362528e-01 -5.78330550e-03
      7.41958439e-01 -1.37246147e-01 7.00579703e-01 -9.08543840e-02
      -9.35468435e-01 0. 6.82624102e-01 -3.40383410e-01 -6.97051644e-01
      -2.99835265e-01 1.33387768e+00 -7.22560823e-01 6.88033998e-01
      -9.18130800e-02 4.31465775e-01 -1.20205104e+00 4.10351902e-01
      8.37743640e-01 -1.75437942e-01 -5.01277074e-02 -5.33406556e-01
      -7.63965786e-01 -6.57025933e-01 7.29824081e-02 1.54415756e-01
      7.79626250e-01 1.16151638e-01 -4.49331701e-01 6.22404337e-01
      -6.14695847e-01 1.58043408e+00 -6.38255119e-01 3.66483070e-02
      -1.87928706e-01 -9.72553551e-01 -1.25248238e-01 7.78231084e-01 0.
      -1.97981410e-02 -2.67609805e-01 -5.99298365e-02 -3.31392556e-01
      5.75720258e-02 -2.48375341e-01 -1.77837145e+00 -4.49174911e-01
      3.57817113e-01 -2.41668865e-01 -5.48822284e-01 2.66040534e-01
      5.21466546e-02 6.94334745e-01 5.19867718e-01 1.53759316e-01
      3.28014821e-01 2.31126040e-01 -5.89144409e-01 -8.26958656e-01
      4.27968860e-01 -7.38483155e-03 9.63305414e-01 -1.47468671e-01
      -5.28215051e-01 -1.47832453e-01 -3.67790133e-01 1.22076921e-01
      -1.13563871e+00 2.31603354e-01 1.76461786e-01 0. 6.77239418e-01
      7.91535914e-01 -1.31365907e+00 2.78128982e-01 9.69819188e-01
      5.26100816e-03 1.10622096e+00 -2.79502273e-02 -4.84919012e-01
      1.39809334e+00 -1.56514430e+00 9.37072262e-02 -3.72580022e-01
      -2.43184809e-02 -4.90491211e-01 -3.00337076e-01 -2.33995810e-01
      2.13349298e-01 1.84588749e-02 1.96925923e-01 4.32492673e-01
      5.38777933e-02 -8.29876363e-01 -6.96018755e-01 1.66306937e+00
      6.04285523e-02 1.35702825e+00 -6.33150339e-01 5.19512117e-01
      4.59412664e-01 -6.38474897e-03 0. -4.59847301e-01 -8.61790478e-01
      2.19935715e-01 3.81609619e-01 -3.61596316e-01 9.36905921e-01
      5.95700145e-01 -2.83447146e-01 -7.05682814e-01 -3.22011679e-01
      4.78545249e-01 -9.79696870e-01 -1.67199597e-01 -3.35854366e-02
      7.48990536e-01 -1.17858219e+00 -5.20607769e-01 2.70906370e-02
      -7.34640718e-01 2.33297616e-01 7.47738957e-01 2.12514028e-02
      -3.53787839e-01 -2.97388166e-01 8.36899281e-02 2.58403242e-01
      2.38786960e+00 2.15349257e-01 -6.14855886e-01 6.21868819e-02
      -8.34235787e-01 0. 5.92983723e-01 -5.32781959e-01 -3.36720318e-01
      1.19800174e+00 -6.92251742e-01 -1.36364937e+00 -5.19022226e-01
      5.03000677e-01 8.42725039e-01 -2.37201974e-01 -2.32483014e-01
      -6.53403878e-01 -6.03788137e-01 4.15135354e-01 -5.04655600e-01
      -3.38028342e-01 -3.65027785e-01 6.76659584e-01 1.06950009e+00
      4.60368156e-01 5.84369600e-01 9.65822786e-02 -3.33531760e-02
      6.43645883e-01 2.30799064e-01 3.13238591e-01 -3.85037921e-02
      -1.52001753e-01 -3.96606559e-03 -1.71927735e-01 -6.85853779e-01 0.
      4.84776109e-01 1.48383141e-01 -2.05199456e+00 -5.30634642e-01
      -1.02673769e+00 1.33508456e+00 1.56957582e-01 3.55589926e-01
      -2.12233573e-01 -2.97004849e-01 2.54231632e-01 9.86982286e-01
      4.63824600e-01 7.95624018e-01 -1.51153886e+00 -1.17338307e-01
      2.73831159e-01 -1.32479656e+00 -3.87881249e-01 1.82069942e-01
      4.21508729e-01 -7.13427663e-02 6.79890811e-02 -3.92243594e-01
      -1.64177269e-02 9.71460044e-01 -7.38738239e-01 -8.08835700e-02
      -4.25984800e-01 2.81071424e-01 -6.30734265e-01 0. -5.54857135e-01
      -3.58575463e-01 6.86436951e-01 -4.22683265e-03 1.12448323e+00
      -8.45077038e-01 -4.56535220e-01 -1.74152470e+00 2.84918338e-01
      5.28997183e-01 -1.24541223e+00 3.34593803e-01 -1.57190681e-01
      -1.80306900e+00 9.59779143e-01 3.38202089e-01 6.88668609e-01
      3.78325641e-01 -4.78797197e-01 -7.60238230e-01 1.01189804e+00
      -7.76582733e-02 -5.35866857e-01 3.82363409e-01 -2.97615528e-01
      3.78406674e-01 1.22575372e-01 3.15120965e-01 -5.63847780e-01
      -6.62931204e-02 -5.53328991e-01 0. -2.85817802e-01 4.70022738e-01
      2.77618080e-01 -4.21898991e-01 -1.16903484e+00 -3.95787448e-01
      6.91388547e-01 -7.92626977e-01 -4.19210374e-01 7.31837094e-01
      9.87693727e-01 -1.26781195e-01 -2.77456939e-01 -1.01053274e+00
      6.19539857e-01 -3.34590495e-01 -4.17035252e-01 -3.66097271e-01
      8.78132522e-01 -7.03759938e-02 1.61898807e-01 2.99777776e-01
      7.36575007e-01 -2.59335846e-01 -5.60631454e-02 7.57297039e-01
      2.60174423e-01 -3.46121788e-02 -8.36910188e-01 -8.59334916e-02
      -9.78999808e-02 0. -1.90369532e-01 -7.90663004e-01 -1.36311263e-01
      9.15765405e-01 7.89193749e-01 -2.20915720e-01 2.99086004e-01
      4.03208941e-01 -7.52945006e-01 -2.77830303e-01 1.82447672e-01
      -5.82682610e-01 -1.09541619e+00 6.34309530e-01 -1.99558794e-01
      -2.40239933e-01 -1.10711670e+00 3.07594746e-01 -8.20635378e-01
      2.11574268e+00 2.46639237e-01 6.59896508e-02 -3.06156695e-01
      1.95973605e-01 -2.39692807e-01 8.85994434e-01 5.24774492e-01
      3.71354036e-02 -6.25594020e-01 2.88149416e-01 -6.71926498e-01 0.
      4.80538726e-01 -3.04229528e-01 3.44015449e-01 -4.64859724e-01
      3.06646794e-01 8.22020411e-01 3.08351099e-01 -4.73812819e-01
      -6.72699332e-01 7.47714162e-01 3.33480924e-01 -9.61917400e-01
      1.11955750e+00 4.61265266e-01 -6.47203922e-01 6.53192848e-02
      2.76819527e-01 -1.01300788e+00 1.19750035e+00 -1.27701652e+00
      -2.82386839e-01 -1.43174314e+00 -5.97952306e-01 9.07307208e-01
      -3.26063901e-01 1.59012973e-01 -6.32625043e-01 -3.63981903e-01
      5.62987983e-01 2.31498495e-01 -8.73259753e-02 0. -2.14882553e-01
      -6.01024926e-01 -1.59548447e-01 2.34612674e-01 8.97922099e-01
      -4.87701148e-02 -1.53351143e-01 -8.73960018e-01 -4.54047680e-01
      -3.64006639e-01 3.84158105e-01 -5.82792222e-01 1.08142149e+00
      -1.59703270e-01 -9.77357447e-01 -3.45030338e-01 -3.05243611e-01
      2.46740967e-01 8.49166811e-01 1.51960835e-01 1.17426515e-01
      3.13575804e-01 1.06998098e+00 5.60743332e-01 -5.67782879e-01
      -5.37712276e-01 4.02679026e-01 -1.00566673e+00 -1.17341734e-01
      -8.36278558e-01 8.30347776e-01 0. 7.76375413e-01 -7.02528834e-01
      1.15839148e+00 -1.17498016e+00 -7.93564379e-01 6.60311878e-01
      2.83487499e-01 -7.58351445e-01 7.69362569e-01 -1.12590873e+00
      -3.44268978e-01 -1.08892441e+00 7.88817465e-01 3.42004269e-01
      -1.12048888e+00 7.25487098e-02 1.11544275e+00 -3.86956334e-01
      -3.19819480e-01 1.92531541e-01 6.28442824e-01 1.06433015e-02
      -8.26487482e-01 7.78936297e-02 -3.00282389e-01 -1.95351586e-01
      1.23424254e-01 -3.27942759e-01 -9.67980921e-01 4.23098505e-01
      1.51945904e-01 0. -9.69504952e-01 6.29109442e-01 -7.25663900e-01
      5.58816731e-01 3.70227665e-01 -6.03199482e-01 -1.28488445e+00
      1.24120462e+00 -7.91499674e-01 8.04172456e-01 -3.41923207e-01
      8.64279449e-01 -4.84272093e-02 -8.07969987e-01 -4.99736071e-02
      1.22145522e+00 -9.91291940e-01 -5.05822361e-01 -2.41141453e-01
      -1.06544830e-01 -3.49838614e-01 -1.96447313e-01 4.86024261e-01
      -9.43383217e-01 3.79956514e-01 4.49698746e-01 -7.65612051e-02
      4.57019985e-01 -2.76123006e-02 -3.06412756e-01 -7.97519267e-01 0.
      -6.49411321e-01 -2.51342595e-01 -7.79150426e-01 -2.71677345e-01
      4.71956491e-01 6.22776389e-01 3.12138557e-01 6.73797280e-02
      -7.70860970e-01 -1.87428191e-01 6.11134619e-03 9.86213610e-02
      -1.18000120e-01 -1.00837588e+00 -1.09480277e-01 5.60546517e-01
      -5.40072799e-01 5.44232070e-01 6.75360978e-01 6.52684808e-01
      -6.00581527e-01 -7.07673788e-01 3.40531439e-01 1.03938460e+00
      1.21407457e-01 3.83516103e-01 9.73540395e-02 -5.47783196e-01
      6.30740821e-01 -9.47016954e-01 -7.97012821e-02 0. 7.52230823e-01
      -6.53281629e-01 -4.11516905e-01 1.08157925e-01 6.64022267e-01
      -1.23583814e-02 -5.56229293e-01 2.65182316e-01 -2.51602381e-01
      2.39415839e-01 -8.29152405e-01 5.26130259e-01 1.49374038e-01
      -4.11497533e-01 5.97256660e-01 9.54312384e-01 -1.13038075e+00
      3.88931692e-01 1.04167056e+00 -8.30660343e-01 1.86883882e-01
      -1.55179024e-01 -3.35651934e-02 -2.27044942e-03 -1.43862712e+00
      -5.91615103e-02 -1.34105790e+00 -4.49969806e-02 -5.87054007e-02
      -1.57109469e-01 4.44183588e-01 0. 1.43772435e+00 -3.74854982e-01
      -6.78892314e-01 -2.33174771e-01 -6.37929961e-02 -5.32801270e-01
      8.90093893e-02 -3.28197852e-02 6.89692855e-01 -5.73544621e-01
      3.65738720e-01 -4.68019098e-01 6.25587821e-01 3.92253041e-01
      -3.39765459e-01 -9.62617517e-01 3.28913540e-01 1.92046016e-01
      4.65752006e-01 4.14979279e-01 -3.35727632e-01 7.73636699e-01
      3.42480570e-01 8.17611277e-01 -2.56587327e-01 5.13207674e-01
      3.88008058e-01 -9.71613526e-01 -6.08769417e-01 1.17550850e+00
      3.39200646e-01 0. -6.89384758e-01 1.46141922e+00 2.01105535e-01
      1.30054057e-02 1.91551015e-01 -1.18196391e-01 1.22984076e+00
      3.84961888e-02 -7.70819068e-01 2.53013283e-01 1.75641686e-01
      -9.06664789e-01 4.32794422e-01 6.95888549e-02 -1.36071742e-01
      8.14910412e-01 1.40167892e-01 -4.68731433e-01 -5.21241009e-01
      1.61190778e-01 -3.64170909e-01 -3.09906542e-01 -1.12114751e+00
      6.49983048e-01 9.79622185e-01 6.43063188e-01 -8.22850391e-02
      3.88866156e-01 2.13816613e-02 7.04824626e-01 -2.04484567e-01 0.
      9.07786861e-02 -6.23384774e-01 -1.19797492e+00 -4.91721928e-01
      6.26658797e-01 -2.16583490e-01 5.77035069e-01 2.18024403e-01
      5.39318085e-01 5.17614782e-01 -5.40312171e-01 2.20594436e-01
      4.17736083e-01 -3.61584514e-01 -4.61114615e-01 2.95546561e-01
      6.12529814e-01 -4.92421657e-01 1.16595976e-01 5.33581197e-01
      -1.99541569e-01 6.30495369e-01 4.28453624e-01 -8.64617050e-01
      4.83663887e-01 -4.54892188e-01 -5.39963722e-01 -4.60066557e-01
      -3.40200603e-01 5.65695345e-01 1.07642494e-01 0. 5.00548363e-01
      6.12607658e-01 3.94443795e-02 7.91245580e-01 -1.25027627e-01
      7.64049888e-01 -5.22868454e-01 -1.24166071e+00 -6.50939286e-01
      2.63262212e-01 -5.23568988e-01 6.03278100e-01 1.24064557e-01
      -6.66655421e-01 9.72662121e-02 2.58144319e-01 1.58270493e-01
      -6.16384149e-01 1.16559513e-01 -2.07725987e-01 -4.37056839e-01
      7.66303301e-01 -9.64228392e-01 4.66137379e-01 5.63732564e-01
      -1.54342920e-01 8.13788116e-01 7.76917517e-01 1.94908734e-02
      -4.83065039e-01 -3.76945734e-01 0. 4.58173454e-01 -8.36645067e-01
      1.85143486e-01 1.20539403e+00 8.89378134e-03 3.51567686e-01
      1.00571297e-01 -1.21177785e-01 1.22039568e+00 -9.06055152e-01
      -3.57377380e-01 3.87898944e-02 6.27170503e-01 3.11374396e-01
      1.81835797e-02 1.96037382e-01 -9.49426830e-01 -2.05298945e-01
      -7.38176227e-01 -1.67898580e-01 6.15332842e-01 9.40582395e-01
      -5.30480891e-02 -6.99782193e-01 -8.18593502e-02 -3.31103325e-01
      1.88974559e-01 4.70221817e-01 -2.13008747e-01 3.67807359e-01
      9.34822485e-03 0. -3.03112507e-01 6.68393373e-01 1.54185072e-02
      4.43643108e-02 1.42656103e-01 -3.81537855e-01 -5.55370033e-01
      -6.35447860e-01 -2.70692617e-01 1.16131103e+00 3.80433053e-01
      2.66163617e-01 -1.02064455e+00 5.30276410e-02 1.72020569e-01
      1.04404247e+00 -3.67166281e-01 2.88978279e-01 5.98605335e-01
      3.24834198e-01 3.22993010e-01 -2.94530481e-01 5.61914027e-01
      -1.33876801e-01 8.75197589e-01 -2.03736827e-01 3.62800062e-01
      1.10978770e+00 4.06090379e-01 -7.73039043e-01 -4.11521196e-01 0.
      2.73618460e-01 -1.73217028e-01 -2.87426472e-01 1.42167464e-01
      3.48830998e-01 1.94891050e-01 -4.28402156e-01 -2.52964824e-01
      -3.35110605e-01 -1.08989072e+00 -5.26684463e-01 4.05795097e-01
      -1.31846952e+00 5.69980800e-01 -1.19967806e+00 5.66121817e-01
      3.67211341e-03 5.31475425e-01 -1.90204740e-01 1.52544780e-02
      4.92479980e-01 7.40608498e-02 -5.14690876e-02 3.42022628e-01
      6.89179599e-01 3.17724556e-01 6.41248971e-02 -1.07846165e+00
      -8.60729069e-02 -1.31316650e+00 1.26370800e+00 0. -5.85669816e-01
      1.81960762e-01 8.14454377e-01 -6.34214282e-01 -1.97226182e-01
      -1.23859130e-01 -3.38956594e-01 -6.10697329e-01 1.20652013e-01
      5.67236006e-01 1.95956975e-02 -3.79215509e-01 7.96997398e-02
      7.44907558e-01 -3.90154779e-01 -7.57764637e-01 1.08164489e+00
      -3.33141148e-01 -1.38509423e-01 4.77874756e-01 2.08126724e-01
      -3.21695447e-01 1.38201737e+00 -3.26503903e-01 -6.88041747e-01
      8.13384950e-01 3.56125653e-01 4.62267995e-01 3.18090528e-01
      -1.15464771e+00 2.50998009e-02 0. -6.83867037e-01 -3.36297244e-01
      1.02575637e-01 8.24202299e-02 2.15985805e-01 -4.02553707e-01
      -8.26079547e-01 -8.08937550e-01 4.15247262e-01 -1.00863743e+00
      -1.23416945e-01 3.09825450e-01 -4.46836293e-01 -1.01209223e+00
      9.40704703e-01 6.45540178e-01 -8.59261274e-01 1.27753770e+00
      -1.83663711e-01 1.00481308e+00 -6.68660030e-02 2.27204278e-01
      -4.44190115e-01 5.08800507e-01 3.10304850e-01 -9.17466938e-01
      9.10630643e-01 -1.36613756e-01 -7.39153564e-01 1.82149529e-01
      -4.93434578e-01 0. -7.63865113e-01 3.64029884e-01 -5.23166656e-01
      -5.87515771e-01 -3.25569004e-01 5.09541035e-01 -1.98288992e-01
      3.80294919e-01 -1.46405876e-01 -3.74795347e-01 9.37670410e-01
      -9.68901396e-01 3.97011817e-01 6.02837086e-01 -7.28677809e-01
      -2.30491012e-01 -1.24984182e-01 -4.50259775e-01 -8.38709772e-02
      7.98824906e-01 -5.89661419e-01 2.15407476e-01 2.87734449e-01
      -1.82275966e-01 3.03908885e-01 -1.04978755e-01 9.41159308e-01
      2.63271064e-01 -2.02857822e-01 -2.93018490e-01 -8.19340527e-01 0.
      6.60217643e-01 -2.55831294e-02 -5.77930748e-01 -1.07890673e-01
      -2.97852248e-01 -1.57946736e-01 -7.34365582e-01 6.77694261e-01
      -8.14924762e-02 -5.29167235e-01 -1.67237684e-01 1.11093175e+00
      -9.99207914e-01 -4.88747835e-01 7.14324474e-01 1.01645559e-01
      -1.49136186e-01 4.22532260e-01 9.44448356e-03 2.10520059e-01
      7.39620984e-01 -6.53005779e-01 -2.99987108e-01 1.74870014e+00
      -5.10580778e-01 1.15550816e-01 5.20240963e-01 -1.22463548e+00
      -3.93646350e-03 3.28353882e-01 6.03606880e-01 0. -1.20017862e+00
      -3.47721100e-01 -4.31351334e-01 -1.47174388e-01 5.38846076e-01
      -2.75336206e-01 4.72757369e-02 -3.13166827e-01 8.91949907e-02
      1.18929416e-01 4.96556848e-01 2.33094245e-01 7.54112601e-01
      -7.81160891e-01 3.94409388e-01 -1.60538256e+00 5.52072525e-01
      -8.10973823e-01 -2.42913272e-02 -7.87830576e-02 1.36332765e-01
      7.50368953e-01 -3.64652336e-01 5.77823997e-01 -1.32381558e-01
      4.80107456e-01 -9.71528068e-02 -1.11321151e+00 1.09223640e+00
      -1.11536312e+00 -1.30763948e-01 0. -2.20442098e-02 -4.63991404e-01
      -7.78987646e-01 3.32628220e-01 6.70539141e-01 -5.97813249e-01
      -8.24634969e-01 8.63323510e-01 -3.31869543e-01 -7.43511796e-01
      8.51572007e-02 1.12674856e+00 -9.88431573e-02 -2.57498711e-01
      -4.60435808e-01 -7.64542103e-01 -8.21562171e-01 9.55455452e-02
      5.91413796e-01 -2.90550172e-01 8.03734064e-01 1.07270658e+00
      -1.13374937e+00 8.43913674e-01 -5.39714515e-01 3.79208624e-01
      9.51622367e-01 -7.74275064e-01 -4.17280644e-01 -8.57442617e-01
      6.38667226e-01 0. 1.22387715e-01 7.57659554e-01 -1.12257433e+00
      7.07984626e-01 1.63369572e+00 -6.38764322e-01 -8.44335184e-02
      1.13088000e+00 6.81877732e-02 -4.71228600e-01 8.53832662e-02
      -7.83828557e-01 -7.24419177e-01 2.31291965e-01 1.08996916e+00
      8.28297913e-01 -9.61057186e-01 -4.82387662e-01 -6.79179728e-01
      4.57593679e-01 -7.10014760e-01 8.70602667e-01 -1.70931184e+00
      1.50237575e-01 1.03978348e+00 2.68182486e-01 5.23516476e-01
      8.70083153e-01 1.10996985e+00 -4.39303607e-01 -8.86896908e-01 0.
      -1.45473769e-02 -7.46673584e-01 2.60935247e-01 -8.31280410e-01
      2.28559434e-01 9.36461389e-01 -3.23059559e-01 -1.41089052e-01
      -5.89936115e-02 2.94748485e-01 -1.68966711e-01 9.69503820e-02
      -5.94598055e-01 1.49486542e+00 6.60233557e-01 1.11280546e-01
      -7.03134894e-01 7.12612748e-01 -3.04293470e-03 -5.92325509e-01
      1.34722638e+00 -4.98789400e-01 -1.40669000e+00 -1.09600738e-01
      1.41806290e-01 9.60663036e-02 7.38351405e-01 -1.36776879e-01
      3.60754877e-01 -5.99606395e-01 9.48051274e-01 0. 4.17418480e-01
      -4.23972830e-02 -2.22168773e-01 -1.65239379e-01 5.84435165e-01
      2.22127438e-01 -1.00786245e+00 5.63720226e-01 -1.01556051e+00
      -2.56112307e-01 7.25820482e-01 -6.21834695e-01 4.69323583e-02
      7.49819219e-01 1.45358288e+00 -3.50944728e-01 -1.16704687e-01
      -3.36554199e-02 -2.75135994e-01 8.37935328e-01 1.50853172e-01
      1.30329624e-01 -6.36171579e-01 -8.36884081e-01 -6.59572184e-01
      1.15185130e+00 -4.83167559e-01 -5.13996840e-01 9.38630104e-01
      -2.90863156e-01 3.05280149e-01 0. -5.81045806e-01 6.93302974e-02
      7.90819287e-01 9.40964967e-02 -3.23347688e-01 1.51208150e+00
      4.34265941e-01 -1.05506802e+00 8.74989927e-01 2.12574154e-01
      -2.73417145e-01 -1.03477252e+00 8.91472280e-01 7.61467040e-01
      2.40017578e-01 -4.26465333e-01 -3.78096551e-01 9.01347995e-02
      -4.31211710e-01 5.56877136e-01 1.94738120e-01 1.15786719e+00
      -4.40571383e-02 -1.27721405e+00 7.69623280e-01 -5.29700875e-01
      5.17575741e-01 -5.02847612e-01 -7.10841358e-01 9.00516748e-01
      1.20837760e+00 0. -4.29046631e-01 -4.01924193e-01 1.08067477e+00
      -1.01969898e+00 -3.48404914e-01 5.36740899e-01 3.21860433e-01
      -7.34063268e-01 -3.15360874e-01 1.88120961e-01 -4.74267155e-02
      -9.91389036e-01 -5.75361311e-01 -4.96265680e-01 4.45200130e-02
      -4.27476317e-01 8.70280981e-01 1.70817021e-02 1.74961165e-01
      7.74058282e-01 7.67455578e-01 -5.15124261e-01 -1.97029799e-01
      -1.07703581e-01 6.30003691e-01 6.62034392e-01 1.25002936e-01
      -9.93299067e-01 7.80429244e-01 -7.81397939e-01 -2.91305840e-01 0.
      -3.66931021e-01 1.22624719e+00 -1.04447804e-01 -6.66758120e-01
      3.59812379e-01 -1.80732206e-01 -3.56854469e-01 -2.61527717e-01
      -5.60651906e-02 3.23812068e-01 -4.51932102e-01 -1.92161947e-02
      -2.20045388e-01 3.09731066e-01 -1.61208604e-02 -3.61870468e-01
      4.31964844e-01 -7.76140273e-01 8.66707563e-02 2.25885481e-01
      -1.05874643e-01 -2.16718867e-01 -6.47359848e-01 7.05358505e-01
      8.37589502e-01 2.30429932e-01 -6.76451921e-01 -5.14300048e-01
      -5.06191254e-01 4.09850746e-01 5.10539152e-02 0. 6.69267476e-01
      7.06510782e-01 -6.93296254e-01 -5.01483858e-01 1.21326971e+00
      -6.25780046e-01 -1.55912757e+00 -5.25124431e-01 3.98074001e-01
      1.08786154e+00 -9.56328750e-01 1.89153743e+00 -8.36425722e-01
      3.36595446e-01 1.77064717e-01 4.54259187e-01 7.16091871e-01
      8.91741514e-01 -1.49093211e+00 4.88854110e-01 -4.94375765e-01
      -9.79504943e-01 7.23081052e-01 -4.43212897e-01 2.34971970e-01
      -2.29144871e-01 4.89913613e-01 2.40364045e-01 4.33746070e-01
      1.58893779e-01 5.07991195e-01 0. -8.73971879e-01 5.77633739e-01
      1.62727618e+00 5.72610855e-01 -3.08464944e-01 6.67138025e-02
      -3.53937447e-02 3.14775519e-02 -1.26818204e+00 4.69442457e-01
      3.38482946e-01 -7.87318647e-01 2.79802326e-02 -6.75489128e-01
      2.81376839e-01 -5.58874547e-01 8.11649263e-01 3.90238613e-01
      1.86179623e-01 -1.91079542e-01 -2.88409024e-01 -5.76193668e-02
      3.52727711e-01 4.99025613e-01 4.24501270e-01 -3.57479662e-01
      7.20802605e-01 -4.55460906e-01 -7.17844516e-02 5.15914857e-02
      7.99594581e-01 0. 4.54884768e-01 -1.33335471e+00 2.81446844e-01
      -6.11299217e-01 6.34124398e-01 -7.47631341e-02 7.14489460e-01
      1.70947158e+00 3.02765965e-01 -8.04377437e-01 3.84229958e-01
      7.28254735e-01 -7.28412390e-01 4.21253324e-01 -6.37356281e-01
      1.01118021e-01 -5.28206170e-01 8.22320819e-01 4.45041835e-01
      7.63148367e-01 -1.32065490e-01 3.51236701e-01 1.10402644e+00
      -8.78889859e-02 -3.38524729e-01 -5.30664384e-01 4.46224585e-02
      2.09594578e-01 7.90843666e-01 -7.78364763e-02 -5.68326488e-02 0.
      8.76603484e-01 6.54150248e-01 -5.84929585e-01 -1.41119516e+00
      -5.08536637e-01 6.00137293e-01 -4.34137285e-01 -4.28444356e-01
      8.48406911e-01 5.30448794e-01 4.75354850e-01 7.73520947e-01
      2.92647868e-01 -3.35633218e-01 8.18971455e-01 -9.78446066e-01
      1.63914764e+00 -9.90173101e-01 -1.57435298e+00 6.59314871e-01
      -1.86912611e-01 3.17305535e-01 -1.37402028e-01 7.67923355e-01
      -1.11831021e+00 -5.42930007e-01 3.63842815e-01 1.61213174e-01
      3.90507936e-01 3.08040734e-02 2.83857614e-01 0. 5.91512561e-01
      -1.01419710e-01 -1.65626228e-01 -6.04760587e-01 1.48509458e-01
      2.66400486e-01 -5.35623908e-01 3.27432901e-01 9.88230228e-01
      -6.57181382e-01 -4.02686566e-01 2.78684109e-01 -4.94090259e-01
      -8.09252337e-02 4.26705748e-01 -1.91829547e-01 -2.31529400e-01
      -3.58751327e-01 -1.83389470e-01 -5.71951151e-01 1.39687210e-01
      7.01622605e-01 7.09723234e-01 -8.16904008e-01 -1.26717359e-01
      5.35182208e-02 3.02638054e-01 4.40065354e-01 -8.82741362e-02
      -2.76810080e-01 -4.50662583e-01 0. 8.04287493e-01 -1.10155433e-01
      -1.45014596e+00 1.07720804e+00 -8.75697613e-01 -1.07582808e-01
      -3.10588181e-01 -3.85725290e-01 1.44714907e-01 -3.85643929e-01
      -1.01185179e+00 -6.13249898e-01 1.06272511e-01 1.88632393e+00
      1.48150638e-01 -1.02768505e+00 -3.69495511e-01 9.96758819e-01
      -2.54127800e-01 8.39096665e-01 6.91212237e-01 -1.45713761e-01
      -8.58618617e-01 -8.12850893e-02 -2.38041520e-01 3.75981808e-01
      9.53413725e-01 -6.32677615e-01 7.45401606e-02 3.68095525e-02
      -1.78279296e-01 0. 6.57341361e-01 -1.07074983e-01 -6.33259654e-01
      -1.08033144e+00 2.53131002e-01 1.37236631e+00 -2.32808627e-02
      -3.08522284e-01 -1.06902877e-02 -1.82566747e-01 -4.12385464e-01
      4.31661755e-01 -3.38819176e-01 -6.23179674e-01 3.12452286e-01
      -3.27269025e-02 3.22279900e-01 -1.48100305e+00 1.78462893e-01
      9.92965698e-03 7.58844376e-01 3.64743680e-01 9.63433444e-01
      2.53256708e-01 1.47397745e+00 6.14679039e-01 -9.56456721e-01
      4.36377287e-01 -3.34683418e-01 -7.29805648e-01 -2.60292232e-01 0.
      1.77075946e+00 -1.15098345e+00 9.23162043e-01 4.28463995e-01
      -4.16228950e-01 -4.71097231e-01 1.83149148e-03 2.81557590e-01
      4.34676498e-01 -1.07493365e+00 4.69100952e-01 -6.68520749e-01
      -8.74616504e-01 3.97432327e-01 -1.05144083e+00 3.63010541e-02
      -3.16459779e-03 -9.72372234e-01 3.85872990e-01 1.22577138e-01
      -2.44736895e-01 3.65876853e-01 9.47384536e-01 2.05509529e-01
      4.12279934e-01 -2.70800442e-01 2.92682678e-01 9.16919857e-02
      1.72779541e-02 -5.17842293e-01 -5.05679071e-01 0. -1.19470382e+00
      3.73178840e-01 1.72462955e-01 5.04083395e-01 -1.00868034e+00
      -6.88221216e-01 4.36350524e-01 1.10586894e+00 -1.01920748e+00
      1.67057109e+00 -9.50818300e-01 1.79013044e-01 -1.18960403e-01
      -6.68417335e-01 5.37115037e-01 -9.73101556e-01 -6.08950853e-01
      5.06873965e-01 9.19104964e-02 3.97611111e-01 -2.87484676e-01
      3.12057436e-01 4.57898766e-01 1.11640215e+00 2.54436135e-01
      -1.49478793e-01 1.19477510e-01 -7.55493462e-01 -2.65557706e-01
      1.69991523e-01 2.82099489e-02 0. -1.02595225e-01 1.77287549e-01
      -2.02466398e-01 1.28339559e-01 7.75763512e-01 3.66313279e-01
      -9.95672286e-01 -5.56601584e-01 -4.10777092e-01 9.58117485e-01
      -1.77266252e+00 2.11777240e-01 6.33131489e-02 4.16793078e-01
      -1.35722494e+00 -7.01968744e-02 7.29160905e-01 -3.02630424e-01
      2.74485856e-01 -1.12413955e+00 5.85141718e-01 1.55470550e+00
      3.25062871e-01 1.12816083e+00 2.53052682e-01 6.52198911e-01
      -3.01911056e-01 -5.06578863e-01 -1.94909737e-01 9.65970531e-02
      -3.11492026e-01 0. -7.53399655e-02 -6.57890588e-02 -1.96062759e-01
      -1.37421146e-01 -4.08487409e-01 -2.56809384e-01 8.57352197e-01
      -1.10797524e+00 6.84730858e-02 5.01945913e-01 8.24562848e-01
      -3.04796517e-01 -1.11313951e+00 3.25550884e-01 1.63109612e+00
      1.11723617e-01 -6.05506122e-01 -1.18512344e+00 2.48688553e-02
      8.21640790e-01 4.46814716e-01 1.64473087e-01 -8.83406162e-01
      -4.15782601e-01 -4.19777095e-01 4.60018992e-01 1.00920391e+00
      3.50847751e-01 -9.05659497e-02 -7.87724257e-01 -7.94831105e-03 0.</_></support_vectors>
  <decision_functions>
    <_>
      <sv_count>1</sv_count>
      <rho>9.9989413531691618e-01</rho>
      <alpha>
        1.</alpha>
      <index>
        0</index></_></decision_functions></my_svm>
</opencv_storage>
